ml_framework_group_02/__init__.py
ml_framework_group_02/accuracy_function.py
ml_framework_group_02/activation_function.py
ml_framework_group_02/bias_init_function.py
ml_framework_group_02/loss_function.py
ml_framework_group_02/neural_network.py
ml_framework_group_02/nn_layer.py
ml_framework_group_02/optimizer_function.py
ml_framework_group_02/pca.py
ml_framework_group_02/utils.py
ml_framework_group_02/visualization.py
ml_framework_group_02/weight_init_function.py
ml_framework_group_02-0.1.1.dist-info/METADATA
ml_framework_group_02-0.1.1.dist-info/WHEEL
ml_framework_group_02-0.1.1.dist-info/top_level.txt
ml_framework_group_02-0.1.1.dist-info/RECORD
